pydaisy/Daisy.py
pydaisy/DaisyTools.py
pydaisy/__init__.py
pydaisy/hydraulic.py
pydaisy-1.0.0.dist-info/METADATA
pydaisy-1.0.0.dist-info/WHEEL
pydaisy-1.0.0.dist-info/top_level.txt
pydaisy-1.0.0.dist-info/RECORD
