Metadata-Version: 2.1
Name: pydaisy
Version: 1.0.0
Summary: Various helper classes to read and manipulate Daisy input and output files.
Home-page: https://github.com/JacobGudbjerg/PyDaisy
Author: Jacob Gudbjerg
Author-email: jacobgudbjerg@gmail.com
License: MPL-2.0
Platform: UNKNOWN
Classifier: Development Status :: 3 - Alpha
Classifier: Intended Audience :: Science/Research
Classifier: Programming Language :: Python :: 3.7
Requires-Dist: pandas
Requires-Dist: numpy
